arjan/__init__.py
arjan/arjan.py
arjan/cli.py
arjan/constants.py
arjan/llm.py
arjan/utils.py
arjan/vector_db.py
arjan/scripts/app.py
arjan-0.0.2.dist-info/METADATA
arjan-0.0.2.dist-info/WHEEL
arjan-0.0.2.dist-info/entry_points.txt
arjan-0.0.2.dist-info/top_level.txt
arjan-0.0.2.dist-info/RECORD
