Metadata-Version: 2.4
Name: arjan
Version: 0.0.2
Summary: Ask any question on your codebase with LLM
Author-email: Chatcharin Sangbutsarakum <chatcharinsang@gmail.com>
License: MIT
Project-URL: Homepage, https://github.com/what-in-the-nim/arjan
Project-URL: Issues, https://github.com/what-in-the-nim/arjan/issues
Requires-Python: >=3.10
Requires-Dist: faiss-cpu
Requires-Dist: httpx
Requires-Dist: langchain
Requires-Dist: streamlit
Requires-Dist: tqdm
